zappa/__init__.py
zappa/async.py
zappa/asynchronous.py
zappa/cli.py
zappa/core.py
zappa/handler.py
zappa/letsencrypt.py
zappa/middleware.py
zappa/policies.py
zappa/utilities.py
zappa/wsgi.py
zappa/ext/__init__.py
zappa/ext/django_zappa.py
zappa_warm-0.54.4.dist-info/LICENSE
zappa_warm-0.54.4.dist-info/METADATA
zappa_warm-0.54.4.dist-info/WHEEL
zappa_warm-0.54.4.dist-info/entry_points.txt
zappa_warm-0.54.4.dist-info/top_level.txt
zappa_warm-0.54.4.dist-info/RECORD
