Metadata-Version: 2.1
Name: zappa-warm
Version: 0.54.4
Summary: Server-less Python Web Services for AWS Lambda and API Gateway
Home-page: https://github.com/Mealing-dev/Zappa
Author: Knewnew Developers
Author-email: dev.knewnew@gmail.com
License: MIT License
Platform: UNKNOWN
Classifier: Environment :: Console
Classifier: License :: OSI Approved :: Apache Software License
Classifier: Operating System :: OS Independent
Classifier: Programming Language :: Python
Classifier: Programming Language :: Python :: 3.6
Classifier: Programming Language :: Python :: 3.7
Classifier: Programming Language :: Python :: 3.8
Classifier: Programming Language :: Python :: 3.9
Classifier: Framework :: Django
Classifier: Framework :: Django :: 1.11
Classifier: Framework :: Django :: 2.0
Classifier: Framework :: Django :: 3.0
Classifier: Topic :: Internet :: WWW/HTTP
Classifier: Topic :: Internet :: WWW/HTTP :: Dynamic Content
License-File: LICENSE
Requires-Dist: argcomplete
Requires-Dist: boto3 (>=1.17.28)
Requires-Dist: durationpy
Requires-Dist: future
Requires-Dist: hjson
Requires-Dist: jmespath
Requires-Dist: kappa (==0.6.0)
Requires-Dist: pip (>=9.0.1)
Requires-Dist: placebo (<0.10)
Requires-Dist: python-dateutil
Requires-Dist: python-slugify
Requires-Dist: pyyaml
Requires-Dist: requests (>=2.20.0)
Requires-Dist: six
Requires-Dist: toml
Requires-Dist: tqdm
Requires-Dist: troposphere (>=3.0)
Requires-Dist: werkzeug
Requires-Dist: wheel
Requires-Dist: wsgi-request-logger
